ppsi/__init__.py
ppsi/__main__.py
ppsi/client/__init__.py
ppsi/client/__main__.py
ppsi/client/command_codes.py
ppsi/client/command_line.py
ppsi/common/__init__.py
ppsi/common/defined.py
ppsi/common/icon.jpg
ppsi/common/misc.py
ppsi/common/shell.py
ppsi/pspbar/__init__.py
ppsi/pspbar/__main__.py
ppsi/pspbar/battery.py
ppsi/pspbar/classes.py
ppsi/pspbar/command_line.py
ppsi/pspbar/cpu.py
ppsi/pspbar/load_average.py
ppsi/pspbar/network.py
ppsi/pspbar/ram.py
ppsi/pspbar/sway_proto.py
ppsi/pspbar/temperature.py
ppsi/pspbar/timer.py
ppsi/pspbar/uname.py
ppsi/pspbar/shell_dep/netcheck.sh
ppsi/server/__init__.py
ppsi/server/__main__.py
ppsi/server/btconnect.py
ppsi/server/command_line.py
ppsi/server/commands.py
ppsi/server/event_watcher.py
ppsi/server/light.py
ppsi/server/passmenu.py
ppsi/server/powermenu.py
ppsi/server/read_config.py
ppsi/server/remote.py
ppsi/server/server.py
ppsi/server/sway_api.py
ppsi/server/volume.py
ppsi/server/wificonnect.py
ppsi/server/workspaces.py
ppsi/server/config/ppsi.yml
ppsi-21.3.1.dist-info/LICENSE
ppsi-21.3.1.dist-info/METADATA
ppsi-21.3.1.dist-info/WHEEL
ppsi-21.3.1.dist-info/entry_points.txt
ppsi-21.3.1.dist-info/top_level.txt
ppsi-21.3.1.dist-info/RECORD
