Metadata-Version: 2.1
Name: ppsi
Version: 21.3.1
Summary: Psi Python Sway Interface
Home-page: https://github.com/pradyparanjpe/ppsi.git
Author: Pradyumna Paranjape
Author-email: pradyparanjpe@rediffmail.com
License: GPLv3
Platform: linux
Requires-Python: >=3.7
Requires-Dist: psutil
Requires-Dist: python-daemon
Requires-Dist: pyyaml
Requires-Dist: launcher-menus
Requires-Dist: psprint
Requires-Dist: argcomplete
